setup.py
LexTestAuto/AStar.pyd
LexTestAuto/DmReg.dll
LexTestAuto/__init__.py
LexTestAuto/customVar.py
LexTestAuto/customVar.pyd
LexTestAuto/dm.dll
LexTestAuto/dmE.py
LexTestAuto/dmE.pyd
LexTestAuto/globalVar.py
LexTestAuto/globalVar.pyd
LexTestAuto/ld.py
LexTestAuto/publicFuc.py
LexTestAuto/thread.py
LexTestAuto/thread.pyd
LexTestAuto.egg-info/PKG-INFO
LexTestAuto.egg-info/SOURCES.txt
LexTestAuto.egg-info/dependency_links.txt
LexTestAuto.egg-info/not-zip-safe
LexTestAuto.egg-info/requires.txt
LexTestAuto.egg-info/top_level.txt