Metadata-Version: 2.1
Name: LexTestAuto
Version: 0.0.37
Summary: Lex软件工作室测试包
Home-page: UNKNOWN
Author: Lex
Author-email: 2983997560@qq.com
License: MIT
Platform: UNKNOWN
Classifier: Programming Language :: Python :: 3
Classifier: License :: OSI Approved :: MIT License
Classifier: Operating System :: Microsoft :: Windows
Requires-Python: >=3.6
